wraplify/__main__.py
wraplify/conf.py
wraplify/path.py
wraplify-0.2.3.dist-info/METADATA
wraplify-0.2.3.dist-info/WHEEL
wraplify-0.2.3.dist-info/entry_points.txt
wraplify-0.2.3.dist-info/top_level.txt
wraplify-0.2.3.dist-info/RECORD
